[
  {
    "schoolName": "가수원중학교",
    "neisSchoolCode": "7451009",
    "schoolInfoCode": "S060000447",
    "level": "중학교",
    "address": "대전광역시 서구 가수원로 26",
    "latitude": 36.2984686817,
    "longitude": 127.3545599663,
    "foundationType": "공립",
    "coedType": "남여공학"
  },
  {
    "schoolName": "갈마중학교",
    "neisSchoolCode": "7451010",
    "schoolInfoCode": "S060000448",
    "level": "중학교",
    "address": "대전광역시 서구 계룡로326번길 138",
    "latitude": 36.3481686828,
    "longitude": 127.3647621964,
    "foundationType": "공립",
    "coedType": "남여공학"
  },
  {
    "schoolName": "기성중학교",
    "neisSchoolCode": "7451011",
    "schoolInfoCode": "S060000449",
    "level": "중학교",
    "address": "대전광역시 서구 장안로 54",
    "latitude": 36.2499114994,
    "longitude": 127.3413452045,
    "foundationType": "공립",
    "coedType": "남여공학"
  },
  {
    "schoolName": "대덕중학교",
    "neisSchoolCode": "7451012",
    "schoolInfoCode": "S060000450",
    "level": "중학교",
    "address": "대전광역시 유성구 대덕대로 515",
    "latitude": 36.3794261258,
    "longitude": 127.3771625982,
    "foundationType": "공립",
    "coedType": "남여공학"
  },
  {
    "schoolName": "대전가양중학교",
    "neisSchoolCode": "7441012",
    "schoolInfoCode": "S060000249",
    "level": "중학교",
    "address": "대전광역시 동구 비래서로62번길 100",
    "latitude": 36.3508533477,
    "longitude": 127.4486753796,
    "foundationType": "공립",
    "coedType": "남여공학"
  },
  {
    "schoolName": "대전가오중학교",
    "neisSchoolCode": "7441013",
    "schoolInfoCode": "S060000250",
    "level": "중학교",
    "address": "대전광역시 동구 은어송로 79",
    "latitude": 36.3086174168,
    "longitude": 127.4571403638,
    "foundationType": "공립",
    "coedType": "남여공학"
  },
  {
    "schoolName": "대전갑천중학교",
    "neisSchoolCode": "7451013",
    "schoolInfoCode": "S060000451",
    "level": "중학교",
    "address": "대전광역시 서구 월평동로 80",
    "latitude": 36.3619430302,
    "longitude": 127.3691985913,
    "foundationType": "공립",
    "coedType": "남여공학"
  },
  {
    "schoolName": "대전경덕중학교",
    "neisSchoolCode": "7441266",
    "schoolInfoCode": "S060000245",
    "level": "중학교",
    "address": "대전광역시 대덕구 동산초교로63번길 12",
    "latitude": 36.3495756197,
    "longitude": 127.4224306104,
    "foundationType": "사립",
    "coedType": "남여공학"
  },
  {
    "schoolName": "대전관저중학교",
    "neisSchoolCode": "7451014",
    "schoolInfoCode": "S060000452",
    "level": "중학교",
    "address": "대전광역시 서구 관저동로 143",
    "latitude": 36.3055188983,
    "longitude": 127.339886116,
    "foundationType": "공립",
    "coedType": "남여공학"
  },
  {
    "schoolName": "대전관평중학교",
    "neisSchoolCode": "7451015",
    "schoolInfoCode": "S060001174",
    "level": "중학교",
    "address": "대전광역시 유성구 테크노4로 132",
    "latitude": 36.4249113415,
    "longitude": 127.3879446918,
    "foundationType": "공립",
    "coedType": "남여공학"
  },
  {
    "schoolName": "대전괴정중학교",
    "neisSchoolCode": "7451016",
    "schoolInfoCode": "S060001118",
    "level": "중학교",
    "address": "대전광역시 서구 가장로 15",
    "latitude": 36.3403928737,
    "longitude": 127.3788144582,
    "foundationType": "공립",
    "coedType": "남여공학"
  },
  {
    "schoolName": "대전구봉중학교",
    "neisSchoolCode": "7451017",
    "schoolInfoCode": "S060001065",
    "level": "중학교",
    "address": "대전광역시 서구 관저서로 86",
    "latitude": 36.3004315509,
    "longitude": 127.3299732513,
    "foundationType": "공립",
    "coedType": "남여공학"
  },
  {
    "schoolName": "대전글꽃중학교",
    "neisSchoolCode": "7441014",
    "schoolInfoCode": "S060001135",
    "level": "중학교",
    "address": "대전광역시 중구 계룡로918번길 103",
    "latitude": 36.3184715483,
    "longitude": 127.4086859462,
    "foundationType": "공립",
    "coedType": "남여공학"
  },
  {
    "schoolName": "대전남선중학교",
    "neisSchoolCode": "7451018",
    "schoolInfoCode": "S060000453",
    "level": "중학교",
    "address": "대전광역시 서구 월평북로 41",
    "latitude": 36.3631304511,
    "longitude": 127.3722081306,
    "foundationType": "공립",
    "coedType": "남여공학"
  },
  {
    "schoolName": "대전내동중학교",
    "neisSchoolCode": "7451019",
    "schoolInfoCode": "S060000454",
    "level": "중학교",
    "address": "대전광역시 서구 배재로 263",
    "latitude": 36.3326117487,
    "longitude": 127.3703031256,
    "foundationType": "공립",
    "coedType": "남여공학"
  },
  {
    "schoolName": "대전노은중학교",
    "neisSchoolCode": "7451020",
    "schoolInfoCode": "S060000455",
    "level": "중학교",
    "address": "대전광역시 유성구 노은동로 104",
    "latitude": 36.3698994354,
    "longitude": 127.3241866595,
    "foundationType": "공립",
    "coedType": "남여공학"
  },
  {
    "schoolName": "대전느리울중학교",
    "neisSchoolCode": "7451021",
    "schoolInfoCode": "S060001060",
    "level": "중학교",
    "address": "대전광역시 서구 관저중로64번길 84",
    "latitude": 36.2972577971,
    "longitude": 127.3395519148,
    "foundationType": "공립",
    "coedType": "남여공학"
  },
  {
    "schoolName": "대전대문중학교",
    "neisSchoolCode": "7441015",
    "schoolInfoCode": "S060000251",
    "level": "중학교",
    "address": "대전광역시 중구 송리로 33",
    "latitude": 36.30800495,
    "longitude": 127.40078831,
    "foundationType": "공립",
    "coedType": "남여공학"
  },
  {
    "schoolName": "대전대성여자중학교",
    "neisSchoolCode": "7441263",
    "schoolInfoCode": "S060000247",
    "level": "중학교",
    "address": "대전광역시 동구 대성2길 20",
    "latitude": 36.3368600431,
    "longitude": 127.4416269289,
    "foundationType": "사립",
    "coedType": "여"
  },
  {
    "schoolName": "대전대성중학교",
    "neisSchoolCode": "7441264",
    "schoolInfoCode": "S060000248",
    "level": "중학교",
    "address": "대전광역시 중구 목동로 23",
    "latitude": 36.3319870419,
    "longitude": 127.4072106106,
    "foundationType": "사립",
    "coedType": "남"
  },
  {
    "schoolName": "대전대신중학교",
    "neisSchoolCode": "7451022",
    "schoolInfoCode": "S060000456",
    "level": "중학교",
    "address": "대전광역시 서구 오량1길 98",
    "latitude": 36.3089303959,
    "longitude": 127.3801141448,
    "foundationType": "사립",
    "coedType": "남"
  },
  {
    "schoolName": "대전대청중학교",
    "neisSchoolCode": "7441016",
    "schoolInfoCode": "S060001084",
    "level": "중학교",
    "address": "대전광역시 대덕구 신탄진동로 81",
    "latitude": 36.4489620984,
    "longitude": 127.4378086668,
    "foundationType": "공립",
    "coedType": "남여공학"
  },
  {
    "schoolName": "대전대화중학교",
    "neisSchoolCode": "7441017",
    "schoolInfoCode": "S060000252",
    "level": "중학교",
    "address": "대전광역시 대덕구 대오길 9",
    "latitude": 36.361613375,
    "longitude": 127.4147453268,
    "foundationType": "공립",
    "coedType": "남여공학"
  },
  {
    "schoolName": "대전덕명중학교",
    "neisSchoolCode": "7451266",
    "schoolInfoCode": "S060001245",
    "level": "중학교",
    "address": "대전광역시 유성구 학하중앙로 61",
    "latitude": 36.3460601354,
    "longitude": 127.3027351156,
    "foundationType": "공립",
    "coedType": "남여공학"
  },
  {
    "schoolName": "대전도마중학교",
    "neisSchoolCode": "7451023",
    "schoolInfoCode": "S060000457",
    "level": "중학교",
    "address": "대전광역시 서구 도솔2길 22",
    "latitude": 36.3189045737,
    "longitude": 127.3721224675,
    "foundationType": "공립",
    "coedType": "남여공학"
  },
  {
    "schoolName": "대전도안중학교",
    "neisSchoolCode": "7451265",
    "schoolInfoCode": "S060001217",
    "level": "중학교",
    "address": "대전광역시 서구 원도안로 160",
    "latitude": 36.3179638685,
    "longitude": 127.345666142,
    "foundationType": "공립",
    "coedType": "남여공학"
  },
  {
    "schoolName": "대전동산중학교",
    "neisSchoolCode": "7441018",
    "schoolInfoCode": "S060000253",
    "level": "중학교",
    "address": "대전광역시 중구 문화로 183",
    "latitude": 36.3152931964,
    "longitude": 127.4041484035,
    "foundationType": "사립",
    "coedType": "남"
  },
  {
    "schoolName": "대전동화중학교",
    "neisSchoolCode": "7451024",
    "schoolInfoCode": "S060001117",
    "level": "중학교",
    "address": "대전광역시 유성구 관평2로 43",
    "latitude": 36.4228903004,
    "longitude": 127.3897990349,
    "foundationType": "공립",
    "coedType": "남여공학"
  },
  {
    "schoolName": "대전두리중학교",
    "neisSchoolCode": "7451025",
    "schoolInfoCode": "S060001066",
    "level": "중학교",
    "address": "대전광역시 유성구 와룡로 37",
    "latitude": 36.4286276899,
    "longitude": 127.3812455047,
    "foundationType": "공립",
    "coedType": "남여공학"
  },
  {
    "schoolName": "대전둔곡중학교",
    "neisSchoolCode": "7451350",
    "schoolInfoCode": "S060001384",
    "level": "중학교",
    "address": "대전광역시 유성구 과학인재4길 10",
    "latitude": 36.4533443959,
    "longitude": 127.3646271446,
    "foundationType": "공립",
    "coedType": "남여공학"
  },
  {
    "schoolName": "대전둔산중학교",
    "neisSchoolCode": "7451026",
    "schoolInfoCode": "S060000458",
    "level": "중학교",
    "address": "대전광역시 서구 갈마역로25번길 70",
    "latitude": 36.3533110296,
    "longitude": 127.3722816997,
    "foundationType": "공립",
    "coedType": "남여공학"
  },
  {
    "schoolName": "대전둔원중학교",
    "neisSchoolCode": "7451027",
    "schoolInfoCode": "S060000459",
    "level": "중학교",
    "address": "대전광역시 서구 괴정로11번길 73",
    "latitude": 36.3425842598,
    "longitude": 127.376334336,
    "foundationType": "공립",
    "coedType": "남여공학"
  },
  {
    "schoolName": "대전만년중학교",
    "neisSchoolCode": "7451028",
    "schoolInfoCode": "S060000460",
    "level": "중학교",
    "address": "대전광역시 서구 만년남로 17",
    "latitude": 36.3670117378,
    "longitude": 127.3759705724,
    "foundationType": "공립",
    "coedType": "남여공학"
  },
  {
    "schoolName": "대전매봉중학교",
    "neisSchoolCode": "7441019",
    "schoolInfoCode": "S060000255",
    "level": "중학교",
    "address": "대전광역시 대덕구 선비마을로 165",
    "latitude": 36.3692874077,
    "longitude": 127.4361004436,
    "foundationType": "공립",
    "coedType": "남여공학"
  },
  {
    "schoolName": "대전문정중학교",
    "neisSchoolCode": "7451029",
    "schoolInfoCode": "S060000461",
    "level": "중학교",
    "address": "대전광역시 서구 둔산북로 232-11",
    "latitude": 36.3554760192,
    "longitude": 127.4005903462,
    "foundationType": "공립",
    "coedType": "남여공학"
  },
  {
    "schoolName": "대전문지중학교",
    "neisSchoolCode": "7451030",
    "schoolInfoCode": "S060000462",
    "level": "중학교",
    "address": "대전광역시 유성구 전민로 53",
    "latitude": 36.3972196877,
    "longitude": 127.3990789007,
    "foundationType": "공립",
    "coedType": "남여공학"
  },
  {
    "schoolName": "대전문화여자중학교",
    "neisSchoolCode": "7441020",
    "schoolInfoCode": "S060000256",
    "level": "중학교",
    "address": "대전광역시 중구 문화로218번길 63",
    "latitude": 36.3129146127,
    "longitude": 127.409816095,
    "foundationType": "공립",
    "coedType": "여"
  },
  {
    "schoolName": "대전버드내중학교",
    "neisSchoolCode": "7451031",
    "schoolInfoCode": "S060000463",
    "level": "중학교",
    "address": "대전광역시 서구 유등로 285",
    "latitude": 36.3167567142,
    "longitude": 127.3833547282,
    "foundationType": "공립",
    "coedType": "남여공학"
  },
  {
    "schoolName": "대전법동중학교",
    "neisSchoolCode": "7441021",
    "schoolInfoCode": "S060000257",
    "level": "중학교",
    "address": "대전광역시 대덕구 쌍청당로 55",
    "latitude": 36.3666402997,
    "longitude": 127.4334782912,
    "foundationType": "공립",
    "coedType": "남여공학"
  },
  {
    "schoolName": "대전변동중학교",
    "neisSchoolCode": "7451032",
    "schoolInfoCode": "S060000464",
    "level": "중학교",
    "address": "대전광역시 서구 도산로181번길 39",
    "latitude": 36.3245124534,
    "longitude": 127.3759177782,
    "foundationType": "공립",
    "coedType": "남여공학"
  },
  {
    "schoolName": "대전봉명중학교",
    "neisSchoolCode": "7451255",
    "schoolInfoCode": "S060001180",
    "level": "중학교",
    "address": "대전광역시 유성구 계룡로132번길 71",
    "latitude": 36.3496908884,
    "longitude": 127.344997554,
    "foundationType": "공립",
    "coedType": "남여공학"
  },
  {
    "schoolName": "대전봉산중학교",
    "neisSchoolCode": "7451033",
    "schoolInfoCode": "S060000465",
    "level": "중학교",
    "address": "대전광역시 서구 배재로262번길 60",
    "latitude": 36.3308539398,
    "longitude": 127.3733643231,
    "foundationType": "공립",
    "coedType": "남여공학"
  },
  {
    "schoolName": "대전봉우중학교",
    "neisSchoolCode": "7451034",
    "schoolInfoCode": "S060000466",
    "level": "중학교",
    "address": "대전광역시 서구 관저로 102",
    "latitude": 36.2987229916,
    "longitude": 127.3325444626,
    "foundationType": "공립",
    "coedType": "남여공학"
  },
  {
    "schoolName": "대전삼육중학교",
    "neisSchoolCode": "7451035",
    "schoolInfoCode": "S060000468",
    "level": "중학교",
    "address": "대전광역시 서구 도림1길 15",
    "latitude": 36.3119447179,
    "longitude": 127.3730024506,
    "foundationType": "사립",
    "coedType": "남여공학"
  },
  {
    "schoolName": "대전삼천중학교",
    "neisSchoolCode": "7451036",
    "schoolInfoCode": "S060000469",
    "level": "중학교",
    "address": "대전광역시 서구 문정로 271",
    "latitude": 36.3586364821,
    "longitude": 127.3943450053,
    "foundationType": "공립",
    "coedType": "남여공학"
  },
  {
    "schoolName": "대전새미래중학교",
    "neisSchoolCode": "7451303",
    "schoolInfoCode": "S060001290",
    "level": "중학교",
    "address": "대전광역시 유성구 지족동로 55",
    "latitude": 36.3792284764,
    "longitude": 127.3049855252,
    "foundationType": "공립",
    "coedType": "남여공학"
  },
  {
    "schoolName": "대전서중학교",
    "neisSchoolCode": "7451037",
    "schoolInfoCode": "S060000470",
    "level": "중학교",
    "address": "대전광역시 서구 동서대로997번길 57",
    "latitude": 36.3361297512,
    "longitude": 127.3738394878,
    "foundationType": "공립",
    "coedType": "남여공학"
  },
  {
    "schoolName": "대전송강중학교",
    "neisSchoolCode": "7451038",
    "schoolInfoCode": "S060000471",
    "level": "중학교",
    "address": "대전광역시 유성구 와룡로 122",
    "latitude": 36.4376488759,
    "longitude": 127.3816375925,
    "foundationType": "공립",
    "coedType": "남여공학"
  },
  {
    "schoolName": "대전송촌중학교",
    "neisSchoolCode": "7441022",
    "schoolInfoCode": "S060000258",
    "level": "중학교",
    "address": "대전광역시 대덕구 계족산로 110",
    "latitude": 36.3643294348,
    "longitude": 127.4433732228,
    "foundationType": "공립",
    "coedType": "남여공학"
  },
  {
    "schoolName": "대전신계중학교",
    "neisSchoolCode": "7451039",
    "schoolInfoCode": "S060001062",
    "level": "중학교",
    "address": "대전광역시 서구 복수동로 40-30",
    "latitude": 36.3017926512,
    "longitude": 127.3768196346,
    "foundationType": "공립",
    "coedType": "남여공학"
  },
  {
    "schoolName": "대전신일중학교",
    "neisSchoolCode": "7441277",
    "schoolInfoCode": "S060000272",
    "level": "중학교",
    "address": "대전광역시 중구 부사로32번길 27",
    "latitude": 36.3091775698,
    "longitude": 127.4345273146,
    "foundationType": "사립",
    "coedType": "남여공학"
  },
  {
    "schoolName": "대전어은중학교",
    "neisSchoolCode": "7451040",
    "schoolInfoCode": "S060000472",
    "level": "중학교",
    "address": "대전광역시 유성구 농대로 56",
    "latitude": 36.3659861501,
    "longitude": 127.352945059,
    "foundationType": "공립",
    "coedType": "남여공학"
  },
  {
    "schoolName": "대전여자중학교",
    "neisSchoolCode": "7441023",
    "schoolInfoCode": "S060000259",
    "level": "중학교",
    "address": "대전광역시 중구 보문로230번길 69",
    "latitude": 36.3247141888,
    "longitude": 127.426434778,
    "foundationType": "공립",
    "coedType": "여"
  },
  {
    "schoolName": "대전외삼중학교",
    "neisSchoolCode": "7451041",
    "schoolInfoCode": "S060001064",
    "level": "중학교",
    "address": "대전광역시 유성구 반석동로 75",
    "latitude": 36.3942573736,
    "longitude": 127.3102118079,
    "foundationType": "공립",
    "coedType": "남여공학"
  },
  {
    "schoolName": "대전용운중학교",
    "neisSchoolCode": "7441024",
    "schoolInfoCode": "S060000261",
    "level": "중학교",
    "address": "대전광역시 동구 용운로 208",
    "latitude": 36.3255904791,
    "longitude": 127.4650085065,
    "foundationType": "공립",
    "coedType": "남여공학"
  },
  {
    "schoolName": "대전용전중학교",
    "neisSchoolCode": "7441025",
    "schoolInfoCode": "S060000262",
    "level": "중학교",
    "address": "대전광역시 대덕구 한밭대로1146번길 46",
    "latitude": 36.3566020603,
    "longitude": 127.4252271418,
    "foundationType": "공립",
    "coedType": "남여공학"
  },
  {
    "schoolName": "대전원신흥중학교",
    "neisSchoolCode": "7451342",
    "schoolInfoCode": "S060001375",
    "level": "중학교",
    "address": "대전광역시 유성구 동서대로735번길 20",
    "latitude": 36.333077619,
    "longitude": 127.3453319348,
    "foundationType": "공립",
    "coedType": "남여공학"
  },
  {
    "schoolName": "대전월평중학교",
    "neisSchoolCode": "7451042",
    "schoolInfoCode": "S060000473",
    "level": "중학교",
    "address": "대전광역시 서구 월평동로 21",
    "latitude": 36.3564111754,
    "longitude": 127.3675904119,
    "foundationType": "공립",
    "coedType": "남여공학"
  },
  {
    "schoolName": "대전은어송중학교",
    "neisSchoolCode": "7441026",
    "schoolInfoCode": "S060001139",
    "level": "중학교",
    "address": "대전광역시 동구 동구청로 26",
    "latitude": 36.3003797828,
    "longitude": 127.461118055,
    "foundationType": "공립",
    "coedType": "남여공학"
  },
  {
    "schoolName": "대전자운중학교",
    "neisSchoolCode": "7451043",
    "schoolInfoCode": "S060001090",
    "level": "중학교",
    "address": "대전광역시 유성구 자운로97번길 356",
    "latitude": 36.4111166499,
    "longitude": 127.3380265591,
    "foundationType": "공립",
    "coedType": "남여공학"
  },
  {
    "schoolName": "대전장대중학교",
    "neisSchoolCode": "7451044",
    "schoolInfoCode": "S060001061",
    "level": "중학교",
    "address": "대전광역시 유성구 문화원로 26",
    "latitude": 36.3605591476,
    "longitude": 127.3386679398,
    "foundationType": "공립",
    "coedType": "남여공학"
  },
  {
    "schoolName": "대전전민중학교",
    "neisSchoolCode": "7451045",
    "schoolInfoCode": "S060000475",
    "level": "중학교",
    "address": "대전광역시 유성구 엑스포로466번길 97",
    "latitude": 36.4013461577,
    "longitude": 127.4057573555,
    "foundationType": "공립",
    "coedType": "남여공학"
  },
  {
    "schoolName": "대전정림중학교",
    "neisSchoolCode": "7451046",
    "schoolInfoCode": "S060000476",
    "level": "중학교",
    "address": "대전광역시 서구 괴곡길 70",
    "latitude": 36.2938207021,
    "longitude": 127.361075829,
    "foundationType": "공립",
    "coedType": "남여공학"
  },
  {
    "schoolName": "대전중앙중학교",
    "neisSchoolCode": "7441028",
    "schoolInfoCode": "S060000265",
    "level": "중학교",
    "address": "대전광역시 중구 대종로 634",
    "latitude": 36.3384853003,
    "longitude": 127.4145859166,
    "foundationType": "사립",
    "coedType": "남"
  },
  {
    "schoolName": "대전중학교",
    "neisSchoolCode": "7441029",
    "schoolInfoCode": "S060000266",
    "level": "중학교",
    "address": "대전광역시 중구 수도산로 9",
    "latitude": 36.3207688802,
    "longitude": 127.4249032266,
    "foundationType": "공립",
    "coedType": "남"
  },
  {
    "schoolName": "대전지족중학교",
    "neisSchoolCode": "7451048",
    "schoolInfoCode": "S060000477",
    "level": "중학교",
    "address": "대전광역시 유성구 노은동로 193",
    "latitude": 36.3780801954,
    "longitude": 127.3208817677,
    "foundationType": "공립",
    "coedType": "남여공학"
  },
  {
    "schoolName": "대전체육중학교",
    "neisSchoolCode": "7451049",
    "schoolInfoCode": "S060000478",
    "level": "중학교",
    "address": "대전광역시 유성구 원신흥로40번길 6",
    "latitude": 36.3369076608,
    "longitude": 127.3428159571,
    "foundationType": "공립",
    "coedType": "남여공학"
  },
  {
    "schoolName": "대전탄방중학교",
    "neisSchoolCode": "7451050",
    "schoolInfoCode": "S060000479",
    "level": "중학교",
    "address": "대전광역시 서구 문정로 181",
    "latitude": 36.3505584056,
    "longitude": 127.3943309991,
    "foundationType": "공립",
    "coedType": "남여공학"
  },
  {
    "schoolName": "대전태평중학교",
    "neisSchoolCode": "7441030",
    "schoolInfoCode": "S060000267",
    "level": "중학교",
    "address": "대전광역시 중구 수침로111번길 12",
    "latitude": 36.3295402566,
    "longitude": 127.3973301613,
    "foundationType": "공립",
    "coedType": "남여공학"
  },
  {
    "schoolName": "대전하기중학교",
    "neisSchoolCode": "7451051",
    "schoolInfoCode": "S060001116",
    "level": "중학교",
    "address": "대전광역시 유성구 송림로48번길 6-30",
    "latitude": 36.385859198,
    "longitude": 127.3221887661,
    "foundationType": "공립",
    "coedType": "남여공학"
  },
  {
    "schoolName": "동대전중학교",
    "neisSchoolCode": "7441031",
    "schoolInfoCode": "S060000268",
    "level": "중학교",
    "address": "대전광역시 동구 충정로 73-6",
    "latitude": 36.3451917462,
    "longitude": 127.4559326414,
    "foundationType": "공립",
    "coedType": "남여공학"
  },
  {
    "schoolName": "동명중학교",
    "neisSchoolCode": "7441032",
    "schoolInfoCode": "S060000269",
    "level": "중학교",
    "address": "대전광역시 중구 사득로54번길 29",
    "latitude": 36.3083979811,
    "longitude": 127.4387406827,
    "foundationType": "사립",
    "coedType": "남여공학"
  },
  {
    "schoolName": "동방여자중학교",
    "neisSchoolCode": "7451052",
    "schoolInfoCode": "S060000480",
    "level": "중학교",
    "address": "대전광역시 서구 복수중로 27",
    "latitude": 36.3062694027,
    "longitude": 127.3746277174,
    "foundationType": "사립",
    "coedType": "여"
  },
  {
    "schoolName": "동신중학교",
    "neisSchoolCode": "7441033",
    "schoolInfoCode": "S060000270",
    "level": "중학교",
    "address": "대전광역시 동구 동부로 56-22",
    "latitude": 36.3203733117,
    "longitude": 127.4597168444,
    "foundationType": "공립",
    "coedType": "남여공학"
  },
  {
    "schoolName": "보문중학교",
    "neisSchoolCode": "7441034",
    "schoolInfoCode": "S060000271",
    "level": "중학교",
    "address": "대전광역시 동구 우암로 57",
    "latitude": 36.3362528547,
    "longitude": 127.4233922987,
    "foundationType": "사립",
    "coedType": "남"
  },
  {
    "schoolName": "성덕중학교",
    "neisSchoolCode": "7451053",
    "schoolInfoCode": "S060000482",
    "level": "중학교",
    "address": "대전광역시 유성구 신성로 19",
    "latitude": 36.3865539689,
    "longitude": 127.3444826916,
    "foundationType": "사립",
    "coedType": "남여공학"
  },
  {
    "schoolName": "신탄중앙중학교",
    "neisSchoolCode": "7441036",
    "schoolInfoCode": "S060000273",
    "level": "중학교",
    "address": "대전광역시 대덕구 덕암로 233",
    "latitude": 36.4425119032,
    "longitude": 127.4232327377,
    "foundationType": "공립",
    "coedType": "남여공학"
  },
  {
    "schoolName": "신탄진중학교",
    "neisSchoolCode": "7441037",
    "schoolInfoCode": "S060000274",
    "level": "중학교",
    "address": "대전광역시 대덕구 석봉로 15",
    "latitude": 36.4476908759,
    "longitude": 127.4234839524,
    "foundationType": "사립",
    "coedType": "남여공학"
  },
  {
    "schoolName": "오정중학교",
    "neisSchoolCode": "7441038",
    "schoolInfoCode": "S060000260",
    "level": "중학교",
    "address": "대전광역시 대덕구 한남로150번길 135",
    "latitude": 36.3511616929,
    "longitude": 127.4079031182,
    "foundationType": "공립",
    "coedType": "남여공학"
  },
  {
    "schoolName": "우송중학교",
    "neisSchoolCode": "7441039",
    "schoolInfoCode": "S060000254",
    "level": "중학교",
    "address": "대전광역시 동구 동대전로131번길 53",
    "latitude": 36.3353277125,
    "longitude": 127.4431776249,
    "foundationType": "사립",
    "coedType": "남"
  },
  {
    "schoolName": "유성중학교",
    "neisSchoolCode": "7451054",
    "schoolInfoCode": "S060000485",
    "level": "중학교",
    "address": "대전광역시 유성구 상대로 33",
    "latitude": 36.3454699025,
    "longitude": 127.3348150989,
    "foundationType": "공립",
    "coedType": "남여공학"
  },
  {
    "schoolName": "중리중학교",
    "neisSchoolCode": "7441040",
    "schoolInfoCode": "S060000263",
    "level": "중학교",
    "address": "대전광역시 대덕구 중리동로 85",
    "latitude": 36.3665975102,
    "longitude": 127.4273451421,
    "foundationType": "공립",
    "coedType": "남여공학"
  },
  {
    "schoolName": "진잠중학교",
    "neisSchoolCode": "7451055",
    "schoolInfoCode": "S060000486",
    "level": "중학교",
    "address": "대전광역시 유성구 진잠로 60-23",
    "latitude": 36.2966652862,
    "longitude": 127.3177425557,
    "foundationType": "공립",
    "coedType": "남여공학"
  },
  {
    "schoolName": "청란여자중학교",
    "neisSchoolCode": "7441041",
    "schoolInfoCode": "S060000275",
    "level": "중학교",
    "address": "대전광역시 중구 보문로 95번길40",
    "latitude": 36.310939941,
    "longitude": 127.4296333636,
    "foundationType": "사립",
    "coedType": "여"
  },
  {
    "schoolName": "충남여자중학교",
    "neisSchoolCode": "7441042",
    "schoolInfoCode": "S060000276",
    "level": "중학교",
    "address": "대전광역시 중구 동서대로 1368",
    "latitude": 36.3316330669,
    "longitude": 127.4116281969,
    "foundationType": "공립",
    "coedType": "여"
  },
  {
    "schoolName": "충남중학교",
    "neisSchoolCode": "7441043",
    "schoolInfoCode": "S060000277",
    "level": "중학교",
    "address": "대전광역시 동구 계족로 123",
    "latitude": 36.3248309299,
    "longitude": 127.4438754758,
    "foundationType": "공립",
    "coedType": "남"
  },
  {
    "schoolName": "한밭여자중학교",
    "neisSchoolCode": "7441044",
    "schoolInfoCode": "S060000278",
    "level": "중학교",
    "address": "대전광역시 동구 동대전로110번길 74-57",
    "latitude": 36.3297898026,
    "longitude": 127.4490223487,
    "foundationType": "공립",
    "coedType": "여"
  },
  {
    "schoolName": "한밭중학교",
    "neisSchoolCode": "7441045",
    "schoolInfoCode": "S060000279",
    "level": "중학교",
    "address": "대전광역시 동구 태전로 67",
    "latitude": 36.3349543872,
    "longitude": 127.4266509742,
    "foundationType": "공립",
    "coedType": "남"
  },
  {
    "schoolName": "호수돈여자중학교",
    "neisSchoolCode": "7441046",
    "schoolInfoCode": "S060000280",
    "level": "중학교",
    "address": "대전광역시 중구 선화로 50",
    "latitude": 36.3266950721,
    "longitude": 127.4135846038,
    "foundationType": "사립",
    "coedType": "여"
  },
  {
    "schoolName": "회덕중학교",
    "neisSchoolCode": "7441047",
    "schoolInfoCode": "S060000281",
    "level": "중학교",
    "address": "대전광역시 대덕구 신탄진로218번길 22",
    "latitude": 36.4010977405,
    "longitude": 127.4253535007,
    "foundationType": "공립",
    "coedType": "남여공학"
  }
]
